{
  "name": "All Easing Functions Showcase",
  "description": "Side-by-side comparison of all easing functions in Rendervid.",
  "version": "1.0.0",
  "output": { "type": "video", "width": 1920, "height": 1080, "fps": 30, "duration": 4 },
  "inputs": [],
  "defaults": {},
  "composition": {
    "scenes": [
      {
        "id": "all-easings", "startFrame": 0, "endFrame": 120,
        "layers": [
          { "id": "bg", "type": "shape", "position": { "x": 0, "y": 0 }, "size": { "width": 1920, "height": 1080 }, "props": { "shape": "rectangle", "fill": "#0c0a09" } },

          { "id": "title", "type": "text", "position": { "x": 0, "y": 30 }, "size": { "width": 1920, "height": 60 }, "props": { "text": "EASING FUNCTIONS COMPARISON", "fontSize": 48, "fontWeight": "bold", "color": "#ffffff", "textAlign": "center" } },

          { "id": "label1", "type": "text", "position": { "x": 60, "y": 130 }, "size": { "width": 200, "height": 30 }, "props": { "text": "linear", "fontSize": 20, "fontWeight": "600", "color": "#a8a29e", "textAlign": "left" } },
          { "id": "track1", "type": "shape", "position": { "x": 270, "y": 130 }, "size": { "width": 1590, "height": 30 }, "props": { "shape": "rectangle", "fill": "#1c1917", "borderRadius": 15 } },
          { "id": "ball1", "type": "shape", "position": { "x": 270, "y": 130 }, "size": { "width": 30, "height": 30 }, "props": { "shape": "ellipse", "fill": "#f97316" }, "animations": [{ "type": "entrance", "effect": "slideInLeft", "delay": 10, "duration": 80, "easing": "linear" }] },

          { "id": "label2", "type": "text", "position": { "x": 60, "y": 200 }, "size": { "width": 200, "height": 30 }, "props": { "text": "easeInQuad", "fontSize": 20, "fontWeight": "600", "color": "#a8a29e", "textAlign": "left" } },
          { "id": "track2", "type": "shape", "position": { "x": 270, "y": 200 }, "size": { "width": 1590, "height": 30 }, "props": { "shape": "rectangle", "fill": "#1c1917", "borderRadius": 15 } },
          { "id": "ball2", "type": "shape", "position": { "x": 270, "y": 200 }, "size": { "width": 30, "height": 30 }, "props": { "shape": "ellipse", "fill": "#eab308" }, "animations": [{ "type": "entrance", "effect": "slideInLeft", "delay": 10, "duration": 80, "easing": "easeInQuad" }] },

          { "id": "label3", "type": "text", "position": { "x": 60, "y": 270 }, "size": { "width": 200, "height": 30 }, "props": { "text": "easeOutQuad", "fontSize": 20, "fontWeight": "600", "color": "#a8a29e", "textAlign": "left" } },
          { "id": "track3", "type": "shape", "position": { "x": 270, "y": 270 }, "size": { "width": 1590, "height": 30 }, "props": { "shape": "rectangle", "fill": "#1c1917", "borderRadius": 15 } },
          { "id": "ball3", "type": "shape", "position": { "x": 270, "y": 270 }, "size": { "width": 30, "height": 30 }, "props": { "shape": "ellipse", "fill": "#22c55e" }, "animations": [{ "type": "entrance", "effect": "slideInLeft", "delay": 10, "duration": 80, "easing": "easeOutQuad" }] },

          { "id": "label4", "type": "text", "position": { "x": 60, "y": 340 }, "size": { "width": 200, "height": 30 }, "props": { "text": "easeInOutCubic", "fontSize": 20, "fontWeight": "600", "color": "#a8a29e", "textAlign": "left" } },
          { "id": "track4", "type": "shape", "position": { "x": 270, "y": 340 }, "size": { "width": 1590, "height": 30 }, "props": { "shape": "rectangle", "fill": "#1c1917", "borderRadius": 15 } },
          { "id": "ball4", "type": "shape", "position": { "x": 270, "y": 340 }, "size": { "width": 30, "height": 30 }, "props": { "shape": "ellipse", "fill": "#3b82f6" }, "animations": [{ "type": "entrance", "effect": "slideInLeft", "delay": 10, "duration": 80, "easing": "easeInOutCubic" }] },

          { "id": "label5", "type": "text", "position": { "x": 60, "y": 410 }, "size": { "width": 200, "height": 30 }, "props": { "text": "easeInQuart", "fontSize": 20, "fontWeight": "600", "color": "#a8a29e", "textAlign": "left" } },
          { "id": "track5", "type": "shape", "position": { "x": 270, "y": 410 }, "size": { "width": 1590, "height": 30 }, "props": { "shape": "rectangle", "fill": "#1c1917", "borderRadius": 15 } },
          { "id": "ball5", "type": "shape", "position": { "x": 270, "y": 410 }, "size": { "width": 30, "height": 30 }, "props": { "shape": "ellipse", "fill": "#8b5cf6" }, "animations": [{ "type": "entrance", "effect": "slideInLeft", "delay": 10, "duration": 80, "easing": "easeInQuart" }] },

          { "id": "label6", "type": "text", "position": { "x": 60, "y": 480 }, "size": { "width": 200, "height": 30 }, "props": { "text": "easeOutQuart", "fontSize": 20, "fontWeight": "600", "color": "#a8a29e", "textAlign": "left" } },
          { "id": "track6", "type": "shape", "position": { "x": 270, "y": 480 }, "size": { "width": 1590, "height": 30 }, "props": { "shape": "rectangle", "fill": "#1c1917", "borderRadius": 15 } },
          { "id": "ball6", "type": "shape", "position": { "x": 270, "y": 480 }, "size": { "width": 30, "height": 30 }, "props": { "shape": "ellipse", "fill": "#ec4899" }, "animations": [{ "type": "entrance", "effect": "slideInLeft", "delay": 10, "duration": 80, "easing": "easeOutQuart" }] },

          { "id": "label7", "type": "text", "position": { "x": 60, "y": 550 }, "size": { "width": 200, "height": 30 }, "props": { "text": "easeOutBack", "fontSize": 20, "fontWeight": "600", "color": "#a8a29e", "textAlign": "left" } },
          { "id": "track7", "type": "shape", "position": { "x": 270, "y": 550 }, "size": { "width": 1590, "height": 30 }, "props": { "shape": "rectangle", "fill": "#1c1917", "borderRadius": 15 } },
          { "id": "ball7", "type": "shape", "position": { "x": 270, "y": 550 }, "size": { "width": 30, "height": 30 }, "props": { "shape": "ellipse", "fill": "#ef4444" }, "animations": [{ "type": "entrance", "effect": "slideInLeft", "delay": 10, "duration": 80, "easing": "easeOutBack" }] },

          { "id": "label8", "type": "text", "position": { "x": 60, "y": 620 }, "size": { "width": 200, "height": 30 }, "props": { "text": "easeOutElastic", "fontSize": 20, "fontWeight": "600", "color": "#a8a29e", "textAlign": "left" } },
          { "id": "track8", "type": "shape", "position": { "x": 270, "y": 620 }, "size": { "width": 1590, "height": 30 }, "props": { "shape": "rectangle", "fill": "#1c1917", "borderRadius": 15 } },
          { "id": "ball8", "type": "shape", "position": { "x": 270, "y": 620 }, "size": { "width": 30, "height": 30 }, "props": { "shape": "ellipse", "fill": "#14b8a6" }, "animations": [{ "type": "entrance", "effect": "slideInLeft", "delay": 10, "duration": 80, "easing": "easeOutElastic" }] },

          { "id": "label9", "type": "text", "position": { "x": 60, "y": 690 }, "size": { "width": 200, "height": 30 }, "props": { "text": "easeOutBounce", "fontSize": 20, "fontWeight": "600", "color": "#a8a29e", "textAlign": "left" } },
          { "id": "track9", "type": "shape", "position": { "x": 270, "y": 690 }, "size": { "width": 1590, "height": 30 }, "props": { "shape": "rectangle", "fill": "#1c1917", "borderRadius": 15 } },
          { "id": "ball9", "type": "shape", "position": { "x": 270, "y": 690 }, "size": { "width": 30, "height": 30 }, "props": { "shape": "ellipse", "fill": "#0ea5e9" }, "animations": [{ "type": "entrance", "effect": "slideInLeft", "delay": 10, "duration": 80, "easing": "easeOutBounce" }] },

          { "id": "label10", "type": "text", "position": { "x": 60, "y": 760 }, "size": { "width": 200, "height": 30 }, "props": { "text": "easeInExpo", "fontSize": 20, "fontWeight": "600", "color": "#a8a29e", "textAlign": "left" } },
          { "id": "track10", "type": "shape", "position": { "x": 270, "y": 760 }, "size": { "width": 1590, "height": 30 }, "props": { "shape": "rectangle", "fill": "#1c1917", "borderRadius": 15 } },
          { "id": "ball10", "type": "shape", "position": { "x": 270, "y": 760 }, "size": { "width": 30, "height": 30 }, "props": { "shape": "ellipse", "fill": "#a3e635" }, "animations": [{ "type": "entrance", "effect": "slideInLeft", "delay": 10, "duration": 80, "easing": "easeInExpo" }] },

          { "id": "label11", "type": "text", "position": { "x": 60, "y": 830 }, "size": { "width": 200, "height": 30 }, "props": { "text": "easeOutCirc", "fontSize": 20, "fontWeight": "600", "color": "#a8a29e", "textAlign": "left" } },
          { "id": "track11", "type": "shape", "position": { "x": 270, "y": 830 }, "size": { "width": 1590, "height": 30 }, "props": { "shape": "rectangle", "fill": "#1c1917", "borderRadius": 15 } },
          { "id": "ball11", "type": "shape", "position": { "x": 270, "y": 830 }, "size": { "width": 30, "height": 30 }, "props": { "shape": "ellipse", "fill": "#fbbf24" }, "animations": [{ "type": "entrance", "effect": "slideInLeft", "delay": 10, "duration": 80, "easing": "easeOutCirc" }] },

          { "id": "label12", "type": "text", "position": { "x": 60, "y": 900 }, "size": { "width": 200, "height": 30 }, "props": { "text": "easeInOutSine", "fontSize": 20, "fontWeight": "600", "color": "#a8a29e", "textAlign": "left" } },
          { "id": "track12", "type": "shape", "position": { "x": 270, "y": 900 }, "size": { "width": 1590, "height": 30 }, "props": { "shape": "rectangle", "fill": "#1c1917", "borderRadius": 15 } },
          { "id": "ball12", "type": "shape", "position": { "x": 270, "y": 900 }, "size": { "width": 30, "height": 30 }, "props": { "shape": "ellipse", "fill": "#fb923c" }, "animations": [{ "type": "entrance", "effect": "slideInLeft", "delay": 10, "duration": 80, "easing": "easeInOutSine" }] },

          { "id": "footer", "type": "text", "position": { "x": 0, "y": 1010 }, "size": { "width": 1920, "height": 40 }, "props": { "text": "Watch how each ball moves at different speeds • Same duration, different curves", "fontSize": 18, "color": "#57534e", "textAlign": "center" } }
        ]
      }
    ]
  }
}
